LICENSE
README.md
setup.py
xdzx_chenjili_base_python_tools/__init__.py
xdzx_chenjili_base_python_tools.egg-info/PKG-INFO
xdzx_chenjili_base_python_tools.egg-info/SOURCES.txt
xdzx_chenjili_base_python_tools.egg-info/dependency_links.txt
xdzx_chenjili_base_python_tools.egg-info/requires.txt
xdzx_chenjili_base_python_tools.egg-info/top_level.txt
xdzx_chenjili_base_python_tools/base/FileUtil.py
xdzx_chenjili_base_python_tools/base/TimeUtil.py
xdzx_chenjili_base_python_tools/base/__init__.py
xdzx_chenjili_base_python_tools/log/LogUtils.py
xdzx_chenjili_base_python_tools/log/LogUtilsConfig.py
xdzx_chenjili_base_python_tools/log/LogUtilsModels.py
xdzx_chenjili_base_python_tools/log/__init__.py