Metadata-Version: 2.1
Name: xdzx-chenjili-base-python-tools
Version: 0.1.3
Summary: a base python tools package
Home-page: https://gitee.com/AuspiciousChan/base-python-tools
Author: AuspiciousChan
Author-email: AuspiciousChan@163.com
License-File: LICENSE
